NumAdd/__init__.py
NumAdd-1.0.0.dist-info/LICENSE
NumAdd-1.0.0.dist-info/METADATA
NumAdd-1.0.0.dist-info/WHEEL
NumAdd-1.0.0.dist-info/top_level.txt
NumAdd-1.0.0.dist-info/RECORD
