Metadata-Version: 2.1
Name: NumAdd
Version: 1.0.0
Summary: Computations on Numbers
Home-page: https://github.com/RoopSai-PavanTej/NumberFunctions
Author: Roop Sai Pavan Tej Pendyala
Author-email: roopsai84@gmail.com
License: UNKNOWN
Platform: UNKNOWN
Classifier: Programming Language :: Python :: 3
Classifier: License :: OSI Approved :: MIT License
Classifier: Operating System :: OS Independent
